chemics/__init__.py
chemics/atm_pressure.py
chemics/atomic_elements.py
chemics/biomass_composition.py
chemics/chemical_equation.py
chemics/conversions.py
chemics/dimensionless_numbers.py
chemics/gas.py
chemics/gas_mixture.py
chemics/liquid.py
chemics/molecular_weight.py
chemics/proximate_analysis.py
chemics/ultimate_analysis.py
chemics/wood.py
chemics/data/gas-cp-yaws.csv
chemics/data/gas-k-yaws.csv
chemics/data/gas-viscosity-ludwig.csv
chemics/data/gas-viscosity-yaws.csv
chemics/data/liquid-cp-yaws.csv
chemics-24.1.dist-info/METADATA
chemics-24.1.dist-info/WHEEL
chemics-24.1.dist-info/licenses/LICENSE.md
chemics-24.1.dist-info/RECORD
