Metadata-Version: 2.1
Name: chemics
Version: 24.1
Summary: A Python package for chemical engineering
Project-URL: Homepage, https://github.com/wigging/chemics
Author: Gavin Wiggins
License-Expression: MIT
License-File: LICENSE.md
Classifier: License :: OSI Approved :: MIT License
Classifier: Operating System :: OS Independent
Classifier: Programming Language :: Python :: 3
Requires-Dist: matplotlib
Requires-Dist: numpy
Requires-Dist: pandas
Requires-Dist: scipy
